tkoplus/__init__.py
tkoplus/tkoplus.py
tkoplus-0.1.dist-info/LICENSE
tkoplus-0.1.dist-info/METADATA
tkoplus-0.1.dist-info/WHEEL
tkoplus-0.1.dist-info/top_level.txt
tkoplus-0.1.dist-info/RECORD
