Metadata-Version: 2.1
Name: tkoplus
Version: 0.1
Summary: tkoplus
Author: Vahid
Author-email: Vahid <vahidpy3@gmail.com>
Project-URL: Homepage, https://github.com/pypa/sampleproject
Project-URL: Bug Tracker, https://github.com/pypa/sampleproject/issues
Classifier: Programming Language :: Python :: 3
Classifier: License :: OSI Approved :: MIT License
Classifier: Operating System :: OS Independent
Requires-Python: >=3.11
License-File: LICENSE
